CHANGES.txt
CONTRIBUTORS.txt
README.txt
TODO.txt
bootstrap.py
buildout.cfg
setup.cfg
setup.py
plone/__init__.py
plone.recipe.cluster.egg-info/PKG-INFO
plone.recipe.cluster.egg-info/SOURCES.txt
plone.recipe.cluster.egg-info/dependency_links.txt
plone.recipe.cluster.egg-info/entry_points.txt
plone.recipe.cluster.egg-info/namespace_packages.txt
plone.recipe.cluster.egg-info/not-zip-safe
plone.recipe.cluster.egg-info/requires.txt
plone.recipe.cluster.egg-info/top_level.txt
plone/recipe/__init__.py
plone/recipe/cluster/README-win32.txt
plone/recipe/cluster/README.txt
plone/recipe/cluster/__init__.py
plone/recipe/cluster/ctl.py
plone/recipe/cluster/daemon.py
plone/recipe/cluster/nt_service.py
plone/recipe/cluster/pythonservice.exe
plone/recipe/cluster/service.py
plone/recipe/cluster/tests/__init__.py
plone/recipe/cluster/tests/test_docs.py