Metadata-Version: 1.0
Name: plone.recipe.cluster
Version: 1.0.0rc1
Summary: ZC Buildout recipe for organizing startup scripts.
Home-page: http://svn.plone.org/svn/collective/buildout/plone.recipe.cluster
Author: Tarek Ziade
Author-email: tarek@ziade.org
License: ZPL
Keywords: zope2 buildout
Platform: UNKNOWN
Classifier: Framework :: Buildout
Classifier: Intended Audience :: Developers
Classifier: Topic :: Software Development :: Build Tools
Classifier: Topic :: Software Development :: Libraries :: Python Modules
Classifier: License :: OSI Approved :: Zope Public License
